drsa/__init__.py
drsa/_nbdev.py
drsa/functions.py
drsa/model.py
drsa-0.0.3.dist-info/LICENSE
drsa-0.0.3.dist-info/METADATA
drsa-0.0.3.dist-info/WHEEL
drsa-0.0.3.dist-info/entry_points.txt
drsa-0.0.3.dist-info/top_level.txt
drsa-0.0.3.dist-info/RECORD
