Metadata-Version: 2.1
Name: drsa
Version: 0.0.3
Summary: A PyTorch implementation of an adapted Deep Recurrent Survival Analysis model.
Home-page: https://github.com/collinprather/drsa/tree/master/
Author: Collin Prather
Author-email: collin.prather742@gmail.com
License: Apache Software License 2.0
Keywords: pytorch deep learning survival analysis
Platform: UNKNOWN
Classifier: Development Status :: 3 - Alpha
Classifier: Intended Audience :: Developers
Classifier: License :: OSI Approved :: Apache Software License
Classifier: Natural Language :: English
Classifier: Programming Language :: Python :: 3.6
Classifier: Programming Language :: Python :: 3.7
Classifier: Programming Language :: Python :: 3.8
Requires-Python: >=3.6
Requires-Dist: torch (==1.3.1)
Requires-Dist: pytest (==5.4.1)
